dadfes/__init__.py
dadfes/admin.py
dadfes/apps.py
dadfes/models.py
django_admin_data_from_external_service-0.1.2.dist-info/LICENSE
django_admin_data_from_external_service-0.1.2.dist-info/METADATA
django_admin_data_from_external_service-0.1.2.dist-info/WHEEL
django_admin_data_from_external_service-0.1.2.dist-info/RECORD
